# 4-常用指令操作码

### 示例格式

`<index><opcode>[<operand1><operand2>...]<comment>`

* index 指令操作码在数组的下标
* opcode 指令操作码的助记符号
* operandN 操作数，可以 0 至多个
* comment 行尾的注释

### 字符和类型对应关系

| 字符 | 类型 |
| ---- | ---- |
| i    | 整数 |
|l|长整数|
|f|浮点数|
|d|双精度浮点数|
|a|对象引用|

### 常用指令和源码

* 常量入栈指令

  * aconst_null 将 null 压入栈
  * iconst_m1 将 -1 压入栈

  * iconst_x (x 为 0 到 5) 将 x 压入栈
  * lconst_x (x 为 0L 到 1L) 将 x 压入栈
  * fconst_x (x 为 0F 到 3F) 将 x 压入栈
  * dconst_x (x 为 0D 到 1D) 将 x 压入栈
  * bipush n (n 为 -128 到 127) 将 n 压入栈
  * sipush n (n 为 -32768 到 32767) 将 n 压入栈
  * ldc  n 将 int、float、String 型的常量 n 压入栈
  * ldc_w  n 将 int、float、String 型的常量 n 压入栈 (宽索引)
  * ldc2_w n 将 long、float 型的常量 n 压入栈

* 局部变量入栈指令

  * xload_y (x 为 i/l/f/d/a,  y 为 0 到 3) 将第 y 个局部变量压入栈

  * xload n (x 为 i/l/f/d/a) 将第 n 个局部变量压入栈

  * xaload (x 为 i/l/f/d/a/b/c/s) 将 x 型数组指定索引的值压入栈，操作数栈的栈顶应为数组索引，栈顶顺位为数组引用

	```java
  // 示例: 是从数组取值
  public void test(char[] a, int[] b){
  	System.out.println(a[0]);
    System.out.println(b[10]);
  }
    
   0: getstatic #2 <java/lang/System.out>
   3: aload_1
   4: iconst_0
   5: caload
   6: invokevirtual #3 <java/io/PrintStream.println>
   9: getstatic #2 <java/lang/System.out>
  12: aload_2
  13: bipush 10
  15: iaload
  16: invokevirtual #3 <java/io/PrintStream.println>
  19: return
  ```
  
* 出栈装入局部变量表指令

  * xstore_y (x 为 i/l/f/d/a,  y 为 0 到 3) 将栈顶 x 型数值存入第 y 个局部变量

  * xstore n (x 为 i/l/f/d/a) 将栈顶 x 型数值存入第 n 个局部变量

  * xastore (x 为 i/l/f/d/a/b/c/s) 为 x 型数组赋值，操作数栈顶是值，顺位是数组索引，再顺位是数组引用

  ```java
  // 示例: 为数组赋值
  public void test(int[] b){
  	int i,j,k,x;
    x = 99;
    b[5] = 770;
  }
  
   0: bipush 99
   2: istore 5
   4: aload_1
   5: iconst_5
   6: sipush 770
   9: iastore
  10: return
  ```

* 通用型操作指令
  * nop 占位，啥也不做
  * dup 意为 duplicate 复制，会把栈顶元素复制一份再次压入栈顶
  * dup_x1 会把栈顶元素复制两份压入栈顶
	* dup_x2 会把栈顶元素复制三份压入栈顶
	* dup2 复制栈顶一个 (对于 long 或者 double 类型) 或两个 (非 long 或者 double) 压入栈顶
	* dup2_x1类似 dup_x1
	* dup2_x2类似 dup_x2
	* pop 把一个元素从栈顶弹出并直接废弃
	* pop2  将栈顶一个 (对于 long 或者 double 类型) 或两个 (非 long 或者 double) 弹出
	
	```java
	public void test(){
		Object obj = new Object();
	  obj.toString();
	}
	
	 0: new #4 <java/lang/Object>
	 3: dup // 栈顶对象被复制了一份压入栈
	 4: invokespecial #1 <java/lang/Object.<init>> // 执行构造函数消耗了一次栈顶对象
	 7: astore_1 // 又消耗了一次栈顶对象，没了
	 8: aload_1 // 取出对象压入栈
	 9: invokevirtual #5 <java/lang/Object.toString> // 此时函数的返回值在栈顶，但没被使用
	12: pop // pop 出多余栈顶对象
	13: return
	```

* 类型转换指令

  * x2y (x 的取值为 i/l/f/d, y 的取值为 i/l/f/d/b/c/s)，x 型数值转 y 型，不包含 b2i, c2i, si2

  ```java
  public void test(int i){
  	long l = i;
    float f = l;
    int j = (int)l;
  }
  
   0: iload_1
   1: i2l
   2: lstore_2
   3: lload_2
   4: l2f
   5: fstore 4 // long 会占 2 个 Slot, 所以局部变量表索引应该变为 4
   7: lload_2
   8: l2i
   9: istore 5
  11: return
  
  ----------  
  public void test(byte i, char j){
  	int k = i;
    long l = j;
    short s = i;
  }
  
   0: iload_1
   1: istore_3
   2: iload_2
   3: i2l
   4: lstore 4
   6: iload_1
   7: i2s
   8: istore 6
  10: return
  ```

* 运算指令

  * 加法 xadd (x 为 i/l/f/d)
  * 减法 xsub (x 为 i/l/f/d)
  * 乘法 xmul (x 为 i/l/f/d)
  * 除法 xdiv (x 为 i/l/f/d)
  * 取余 xrem (x 为 i/l/f/d)
  * 数值取反 xneg (x 为 i/l/f/d)
  * 自增 iinc x, y对给定局部变量做自增操作，完全不修改操作数栈，接收两个参数，第 1 个 x 是局部变量表的位置，第 2 个 y 是累加数
  * 位运算
    * 向左位移 xshl (x 为 i/l/ul)
    * 向右位移 xshr (x 为 i/l/ul)
    * 或 ior, lor
    * 与 iand, land
    * 异或 ixor, lxor

  ```java
  public void test(){
  	float i = 8f;
    float j = -i;
    i = -j;
  }
  
   0: ldc #4 <8.0>
   2: fstore_1
   3: fload_1
   4: fneg
   5: fstore_2
   6: fload_2
   7: fneg
   8: fstore_1
   9: return
     
  ------------------
  public void test(){
  	int i = 123;
    i += 10;
  }
  
   0: bipush 100
   2: istore_1
   3: iinc 1, 10
   6: return
  ```

* 对象/数组操作指令

  * 创建指令
    * new x 创建普通对象，接收一个操作数 x，为指向常量池的索引，表示要创建的类型，执行完成后将对象的引用压入栈
    * newarray x 创建基本类型数组，接收一个操作数 x，为基本数据类型
    * anewarray x 创建对象数组,  x 表示要创建的数组类型
    * multianewarray x, y 创建多维数组，接收两个操作数，x 为运行时常量池的索引，表示要创建的数组类型，y 为实际维数

  ```java
  public void test(){
  	Object obj = new Object();
    int[] array0 = new int[5];
    String[] array1 = new String[1000];
    int[][][] array2 = new int[4][7][1];
  }
  
   0: new #4 <java/lang/Object>
   3: dup
   4: invokespecial #1 <java/lang/Object.<init>>
   7: astore_1
   8: iconst5
   9: newarray int
  11: astore_2 
  12: sipush 1000
  15: anewarray #5 <java/lang/String>
  18: astore_3
  19: iconst4
  20: bipush 7
  22: iconst_1
  23: multianewarray #6 <[[[I> , 3
  27: astore 4
  29: return
  ```

  * 字段访问指令

    * getfield x 获取实例对象字段值，x 为常量池 Fieldref 索引
    * putfield x 将栈顶数值设置为实例对象字段值，x 为常量池 Fieldref 索引
    * getstatic x 获取静态变量值，x 为常量池 Fieldref 索引
    * putstatic x 将栈顶数值设置为静态变量值，x 为常量池 Fieldref 索引

  * 类型检查指令

    * checkcast 检查类型强制转换是否可以进行，若可进行该指令不会改变操作数栈，否则抛出 ClassCastException 异常
    * instanceof 判断给定对象是否是某一个类的实例并将判断结果压入操作数栈，1 是 0 否

    ```java
    public String test(Object obj){
    	if(obj instanceof String){
        return (String)obj;
      }	else {
        return null;
      }
    } 
    
     0: aload_1
     1: instanceof #4 <java/lang/String>
     4: ifeq 12 // 跳转到 12 行
     7: aload_1
     8: checkcast #4 <java/lang/String>
    11: areturn
    12: aconst_null
    13: areturn
    ```

  * 数组操作指令

    * 前文提过的 xaload
    * 前文提过的 xastore
    * arraylength 弹出栈顶的数组元素，获取数组长度并压入栈

* 比较控制指令

  * 比较指令

    * lcmp 比较栈顶两 long 型数值大小并将返回结果 (1/0/-1) 压入栈顶
    * fcmpl 类似上条，当其中一个数值为 NaN 时将 -1 压入栈顶
    * fcmpg 类似上条，当其中一个数值为 NaN 时将 1 压入栈顶
    * dcmpl 类似上条，当其中一个数值为 NaN 时将 -1 压入栈顶
    * dcmpg 类似上条，当其中一个数值为 NaN 时将 1 压入栈顶

  * 条件跳转指令，弹出栈顶 int 型数值，若满足条件则跳转到指定位置。通常结合比较指令使用，接收两个字节的操作数，用于计算跳转的位置

    * ifeq x 表示 == 0 时跳转，x 为要跳转的位置，下同
    * ifne x 表示  != 0 时跳转
    * iflt x 表示 < 0 时跳转
    * ifle x 表示 <= 0 时跳转
    * ifgt x 表示 > 0 时跳转
    * ifge x 表示 >= 0 时跳转
    * ifnull x 表示 == null 时跳转
    * ifnonnull x 表示 != null 时跳转

    ```java
    public void test(){
    	float i = 3.5f;
      float j = 4f;
      System.out.println(i > j);
    } 
    
     0: ldc #4 <3.5>
     2: fstore_1
     3: ldc #5 <4.0>
     5: fstore_2
     6: getstatic #6 <java/lang/System.out>
     9: fload_1
    10: fload_2
    11: fcmpl
    12: ifle 19
    15: iconst_1
    16: goto 20
    19: iconst_0
    20: invokevirtual #7 <java/io/PrintStream.println>
    23: return
    ```

  * 比较条件跳转指令，类似于比较指令和条件跳转指令的结合，分为 int (包括 short, byte, char) 和对象两种，都是栈中最顶两个元素作比较，指令执行完清空栈中这两个元素，且没有任何数据入栈，如果满足条件就跳转，否则就执行下一条语句

    * if_icmpeq x 表示 == 0 时跳转，x 为要跳转的位置，下同
    * if_icmpne x 表示 != 0 时跳转
    * if_icmplt x 表示 < 0 时跳转
    * if_icmple x 表示 <= 0 时跳转
    * if_icmpgt x 表示 > 0 时跳转
    * if_icmpge x 表示 >= 0 时跳转
    * if_acmpeq x 表示 == null 时跳转
    * if_acmpne x 表示 != null 时跳转

    ```java
    public void test(){
    	char i = 3;
      short j = 4;
      System.out.println(i > j);
    } 
    
     0: iconst3
     1: istore1
     2: iconst4
     3: istore2
     4: getstatic #6 <java/lang/System.out>
     7: iload_1
     8: iload_2
     9: if_icmple 16
    12: iconst_1
    13: goto 17
    16: iconst_0
    17: invokevirtual #7 <java/io/PrintStream.println>
    20: return
    ```

  * 多条分支跳转指令，为 switch-case 设计

    * tableswitch 要求多条件分支值是连续的，内部只存放起始值和终止值以及若干跳转偏移量，效率高

      ```java
      public void test(int i) {
      	switch (i) {
        	case 1:
          	System.out.println("a");
      			break;
          case 2:
          	System.out.println("b");
            break;
          case 5:
          	System.out.println("c");
            break;
      	}
      }
      
       0: iload1
       1: tableswitch {
       			1: 36
       			2: 47
       			3: 66
       			4: 66
       			5: 58
       			default: 66
       		}
      36: getstatic #4 <java/lang/System.out>
      39: ldc #5 <a>
      41: invokevirtual #6 <java/io/PrintStream.println>
      44: goto 66
      47: getstatic #4 <java/lang/System.out>
      50: ldc #7 <b>
      52: invokevirtual #6 <java/io/PrintStream.println>
      55: goto 66
      58: getstatic #4 <java/lang/System.out>
      61: ldc #8 <c>
      63: invokevirtual #6 <java/io/PrintStream.println>
      66: return
      ```

    * lookupswitch 内部存放离散的 case-offset 对，每次执行要搜索全部 case-offset 对，找到匹配的 case 并根据对应的 offset 计算跳转地址，效率低。为提高效率会进行排序。

      ```java
      public void test(int i) {
      	switch (i) {
        	case 10:
          	System.out.println("a");
      			break;
          case 2:
          	System.out.println("b");
            break;
          case 5:
          	System.out.println("c");
            break;
      	}
      }
      
       0: iload_1
       1: lookupswitch {
                  2:  47
                  5:  58
                 10:  36
            default:  66
      		}
      36: getstatic #4 <java/lang/System.out>
      39: ldc #5 <a>
      41: invokevirtual #6 <java/io/PrintStream.println>
      44: goto 66
      47: getstatic #4 <java/lang/System.out>
      50: ldc #7 <b>
      52: invokevirtual #6 <java/io/PrintStream.println>
      55: goto 66
      58: getstatic #4 <java/lang/System.out>
      61: ldc #8 <c>
      63: invokevirtual #6 <java/io/PrintStream.println>
      66: return
      ```

  * 无条件跳转指令

    * goto 无条件跳转
    * goto_w 无条件跳转 (宽索引)

* 函数调用

  * invokevirtual x 虚函数调用，调用对象的实例方法，根据对象的实际类型进行派发，支持多态，是最常用的方式，x 是方法的引用，操作完成后，如果该函数不是返回 void 则会将返回结果压入栈中，下同
  * invokeinterface x, y 接口方法调用，被调用对象声明为接口时使用，y 是所传参数的个数
  * invokespecial x 调用特殊方法，如构造函数、类的私有方法、父类方法 (使用 super.xxx() 直接调用父类方法)，这些方法是静态类型绑定的，不会在调用时进行动态派发
  * invokestatic x 调用静态方法，也是静态绑定的
  * invokedynamic x 调用动态绑定的方法，JDK 1.7 加入

  ```java
  public void test() {
  	Thread t = new Thread();
  	t.run();
  	((Runnable)t).run();
    super.toString();
  	go();
  }
  
  private int go(){
  	// 一个私有方法  
    return 1;
  }
  
   0: new #8 <java/lang/Thread>
   3: dup
   4: invokespecial #9 <java/lang/Thread.<init>>
   7: astore_1
   8: aload_1
   9: invokevirtual #10 <java/lang/Thread.run>
  12: aload_1
  13: invokeinterface #11 <java/lang/Runnable.run>, 1
  18: aload_0
  19: invokespecial #12 <java/lang/Object.toString>
  22: pop
  23: aload_0
  24: invokespecial #12 <TestClass.go>
  27: istore_2
  28: return
  ```

* 返回指令

  * return 方法返回 void
  * xreturn (x 为 i/l/f/d/a) 方法返回 x 类型数值

* 异常处理

  // todo

* 同步控制指令

  * monitorenter 在 Java 虚拟机中，任何对象都有一个监视器与之相关联。当一个线程进入同步块时，使用该指令请求进入，如果对象的监视器计数器为 0，则准许进入；若为 1，则判断持有当前监视器的现成是否为自己，如果是则进入，否则进行等待，直到对象的监视器计数器为 0 才允许进入
  * monitorexit 当线程退出同步块时，需要使用该指令声明退出

  ```java
  public class Test {
    public void test() {
      int i = 0;
      synchronized (Test.class){
        i += 1;
      }
    }
  }
  
   0: iconst_0
   1: istore_1
   2: ldc #2 <Test>
   4: dup
   5: astore_2
   6: monitorenter
   7: iinc 1, 1
  10: aload_2
  11: monitorexit
  12: goto 20
  15: astore_3
  16: aload_2
  17: monitorexit
  18: aload_3
  19: athrow
  20: return
  ```

  